fftarray/__init__.py
fftarray/py.typed
fftarray/_src/__init__.py
fftarray/_src/array.py
fftarray/_src/compat_namespace.py
fftarray/_src/constraint_solver.py
fftarray/_src/constraint_solver_exceptions.py
fftarray/_src/creation_functions.py
fftarray/_src/defaults.py
fftarray/_src/dimension.py
fftarray/_src/elementwise_functions.py
fftarray/_src/formatting.py
fftarray/_src/helpers.py
fftarray/_src/indexing.py
fftarray/_src/jax_pytrees.py
fftarray/_src/manipulation_functions.py
fftarray/_src/named_array.py
fftarray/_src/op_lazy_luts.py
fftarray/_src/space.py
fftarray/_src/statistical_functions.py
fftarray/_src/tools.py
fftarray/_src/transform_application.py
fftarray/_src/uniform_value.py
fftarray-0.5.2.dist-info/METADATA
fftarray-0.5.2.dist-info/WHEEL
fftarray-0.5.2.dist-info/licenses/LICENSE
fftarray-0.5.2.dist-info/RECORD
