Metadata-Version: 2.4
Name: fftarray
Version: 0.5.2
Summary: A library to manage and effiently implement all complexities around the complex Fast Fourier Transform.
Project-URL: Homepage, https://github.com/QSTheory/fftarray
Project-URL: Documentation, https://qstheory.github.io/fftarray/main
Project-URL: Repository, https://github.com/QSTheory/fftarray
Project-URL: Issues, https://github.com/QSTheory/fftarray/issues
Project-URL: Changelog, https://qstheory.github.io/fftarray/main/changelog.html
Author: Stefan Seckmeyer, Christian Struckmann, Gabriel Müller, Jan-Niclas Kirsten-Siemß
License-File: LICENSE
Classifier: Intended Audience :: Developers
Classifier: Intended Audience :: Science/Research
Classifier: License :: OSI Approved :: Apache Software License
Classifier: Operating System :: OS Independent
Classifier: Programming Language :: Python
Classifier: Programming Language :: Python :: 3
Classifier: Programming Language :: Python :: 3.11
Classifier: Programming Language :: Python :: 3.12
Classifier: Programming Language :: Python :: 3.13
Classifier: Topic :: Scientific/Engineering
Classifier: Typing :: Typed
Requires-Python: >=3.11
Requires-Dist: array-api-compat>=1.11.0
Requires-Dist: numpy>=2.0
Provides-Extra: dimsolver
Requires-Dist: z3-solver; extra == 'dimsolver'
